pygments_plugin_simstm/__init__.py
pygments_plugin_simstm/simstm_lexer.py
pygments_plugin_simstm-0.0.0a3.dist-info/METADATA
pygments_plugin_simstm-0.0.0a3.dist-info/WHEEL
pygments_plugin_simstm-0.0.0a3.dist-info/entry_points.txt
pygments_plugin_simstm-0.0.0a3.dist-info/licenses/LICENSE
pygments_plugin_simstm-0.0.0a3.dist-info/RECORD
