Metadata-Version: 2.4
Name: pygments-plugin-simstm
Version: 0.0.0a3
Summary: A Pygments lexer plugin for SimStm
Author-email: Denis Vasilik <office@eccelerators.com>
License: MIT
License-File: LICENSE
Classifier: Development Status :: 4 - Beta
Classifier: Programming Language :: Python
Classifier: Programming Language :: Python :: 3.8
Classifier: Programming Language :: Python :: 3.9
Classifier: Programming Language :: Python :: 3.10
Classifier: Programming Language :: Python :: 3.11
Classifier: Programming Language :: Python :: 3.12
Requires-Python: >=3.8
Requires-Dist: pygments>=2.0
Provides-Extra: dev
Requires-Dist: pytest; extra == 'dev'
Requires-Dist: twine; extra == 'dev'
